clayhead/__init__.py
clayhead/async_client.py
clayhead-0.1.0.dist-info/WHEEL
clayhead-0.1.0.dist-info/METADATA
clayhead-0.1.0.dist-info/RECORD
