Metadata-Version: 2.1
Name: clayhead
Version: 0.1.0
Summary: Official Clayhead client SDK for Python
Author: Bo Powers
Author-email: bo@clayhead.ai
Requires-Python: >=3.9,<4.0
Classifier: Programming Language :: Python :: 3
Classifier: Programming Language :: Python :: 3.10
Classifier: Programming Language :: Python :: 3.9
Requires-Dist: black (>=22.6.0,<23.0.0)
Requires-Dist: python-socketio[asyncio_client] (>=5.7.1,<6.0.0)
